<EIFFEL_CLASS_DIAGRAM><VIEW IS_UML="False" NAME="DEFAULT:BON"><ANCESTOR_DEPTH>2</ANCESTOR_DEPTH><DESCENDANT_DEPTH>5</DESCENDANT_DEPTH><CLIENT_DEPTH>0</CLIENT_DEPTH><SUPPLIER_DEPTH>0</SUPPLIER_DEPTH><ALL_CLASSES_IN_CLUSTER>False</ALL_CLASSES_IN_CLUSTER><ONLY_CLASSES_IN_CLUSTER>False</ONLY_CLASSES_IN_CLUSTER><CENTER_CLASS_NAME>OPERATION</CENTER_CLASS_NAME><CENTER_CLASS_GROUP_ID>36ACE60F-96C1-445E-9755-6F88602EB468@tictac@tictac</CENTER_CLASS_GROUP_ID><INHERITANCE_LINKS_DISPLAYED>True</INHERITANCE_LINKS_DISPLAYED><CLIENT_LINKS_DISPLAYED>True</CLIENT_LINKS_DISPLAYED><LABELS_SHOWN>True</LABELS_SHOWN><CLUSTER_SHOWN>True</CLUSTER_SHOWN><HIGH_QUALITY>True</HIGH_QUALITY><LEGEND_SHOWN>False</LEGEND_SHOWN><LEGEND_X_POS>0</LEGEND_X_POS><LEGEND_Y_POS>0</LEGEND_Y_POS><IS_RIGHT_ANGLES>False</IS_RIGHT_ANGLES><SCALE_FACTOR>1</SCALE_FACTOR><ROOT_ELEMENTS><BON_CLASS_FIGURE CLUSTER_NAME="tictac" GROUP_ID="36ACE60F-96C1-445E-9755-6F88602EB468@tictac@tictac" CLASS_FIGURE_ID="A1B353BF-1432-4684-B2D5-335DE303F2FE" NAME="OPERATION"><IS_SELECTED>False</IS_SELECTED><IS_LABEL_SHOWN>True</IS_LABEL_SHOWN><IS_FIXED>True</IS_FIXED><PORT_X>409</PORT_X><PORT_Y>156</PORT_Y><IS_DEFAULT_BG_COLOR_USED>True</IS_DEFAULT_BG_COLOR_USED><IS_NEEDED_ON_DIAGRAM>True</IS_NEEDED_ON_DIAGRAM></BON_CLASS_FIGURE><BON_CLASS_FIGURE CLUSTER_NAME="elks" GROUP_ID="6D7FF712-BBA5-4AC0-AABF-2D9880493A01@base@elks" CLASS_FIGURE_ID="FBC39098-FEEF-4AD8-9000-892BA18608D4" NAME="ANY"><IS_SELECTED>False</IS_SELECTED><IS_LABEL_SHOWN>True</IS_LABEL_SHOWN><IS_FIXED>False</IS_FIXED><PORT_X>423</PORT_X><PORT_Y>60</PORT_Y><IS_DEFAULT_BG_COLOR_USED>True</IS_DEFAULT_BG_COLOR_USED><IS_NEEDED_ON_DIAGRAM>True</IS_NEEDED_ON_DIAGRAM></BON_CLASS_FIGURE><BON_CLASS_FIGURE CLUSTER_NAME="tictac" GROUP_ID="36ACE60F-96C1-445E-9755-6F88602EB468@tictac@tictac" CLASS_FIGURE_ID="417D1DD6-29D9-4194-884F-9B4E543160C3" NAME="MESSAGE"><IS_SELECTED>False</IS_SELECTED><IS_LABEL_SHOWN>True</IS_LABEL_SHOWN><IS_FIXED>False</IS_FIXED><PORT_X>120</PORT_X><PORT_Y>252</PORT_Y><IS_DEFAULT_BG_COLOR_USED>True</IS_DEFAULT_BG_COLOR_USED><IS_NEEDED_ON_DIAGRAM>True</IS_NEEDED_ON_DIAGRAM></BON_CLASS_FIGURE><BON_CLASS_FIGURE CLUSTER_NAME="tictac" GROUP_ID="36ACE60F-96C1-445E-9755-6F88602EB468@tictac@tictac" CLASS_FIGURE_ID="A3CD27ED-74E9-4F0D-B803-63C7FFAFE899" NAME="NEW_GAME"><IS_SELECTED>False</IS_SELECTED><IS_LABEL_SHOWN>True</IS_LABEL_SHOWN><IS_FIXED>False</IS_FIXED><PORT_X>312</PORT_X><PORT_Y>252</PORT_Y><IS_DEFAULT_BG_COLOR_USED>True</IS_DEFAULT_BG_COLOR_USED><IS_NEEDED_ON_DIAGRAM>True</IS_NEEDED_ON_DIAGRAM></BON_CLASS_FIGURE><BON_CLASS_FIGURE CLUSTER_NAME="tictac" GROUP_ID="36ACE60F-96C1-445E-9755-6F88602EB468@tictac@tictac" CLASS_FIGURE_ID="2C19D85F-F167-43CE-8548-0FEA98F657E0" NAME="PLAY"><IS_SELECTED>False</IS_SELECTED><IS_LABEL_SHOWN>True</IS_LABEL_SHOWN><IS_FIXED>False</IS_FIXED><PORT_X>516</PORT_X><PORT_Y>252</PORT_Y><IS_DEFAULT_BG_COLOR_USED>True</IS_DEFAULT_BG_COLOR_USED><IS_NEEDED_ON_DIAGRAM>True</IS_NEEDED_ON_DIAGRAM></BON_CLASS_FIGURE><BON_CLASS_FIGURE CLUSTER_NAME="tictac" GROUP_ID="36ACE60F-96C1-445E-9755-6F88602EB468@tictac@tictac" CLASS_FIGURE_ID="5AAF8D75-BA4B-4513-AEA5-DA6FCC7F6526" NAME="PLAY_AGAIN"><IS_SELECTED>False</IS_SELECTED><IS_LABEL_SHOWN>True</IS_LABEL_SHOWN><IS_FIXED>False</IS_FIXED><PORT_X>692</PORT_X><PORT_Y>252</PORT_Y><IS_DEFAULT_BG_COLOR_USED>True</IS_DEFAULT_BG_COLOR_USED><IS_NEEDED_ON_DIAGRAM>True</IS_NEEDED_ON_DIAGRAM></BON_CLASS_FIGURE><BON_INHERITANCE_FIGURE TARGET="A1B353BF-1432-4684-B2D5-335DE303F2FE" SOURCE="417D1DD6-29D9-4194-884F-9B4E543160C3"><IS_SELECTED>False</IS_SELECTED><IS_LABEL_SHOWN>False</IS_LABEL_SHOWN><IS_DIRECTED>True</IS_DIRECTED><EDGES></EDGES><LINE_WIDTH>2</LINE_WIDTH><LINE_COLOR>230;0;0</LINE_COLOR><IS_NEEDED_ON_DIAGRAM>True</IS_NEEDED_ON_DIAGRAM><REAL_LINE_WIDTH>200</REAL_LINE_WIDTH></BON_INHERITANCE_FIGURE><BON_INHERITANCE_FIGURE TARGET="A1B353BF-1432-4684-B2D5-335DE303F2FE" SOURCE="A3CD27ED-74E9-4F0D-B803-63C7FFAFE899"><IS_SELECTED>False</IS_SELECTED><IS_LABEL_SHOWN>False</IS_LABEL_SHOWN><IS_DIRECTED>True</IS_DIRECTED><EDGES></EDGES><LINE_WIDTH>2</LINE_WIDTH><LINE_COLOR>230;0;0</LINE_COLOR><IS_NEEDED_ON_DIAGRAM>True</IS_NEEDED_ON_DIAGRAM><REAL_LINE_WIDTH>200</REAL_LINE_WIDTH></BON_INHERITANCE_FIGURE><BON_INHERITANCE_FIGURE TARGET="A1B353BF-1432-4684-B2D5-335DE303F2FE" SOURCE="2C19D85F-F167-43CE-8548-0FEA98F657E0"><IS_SELECTED>False</IS_SELECTED><IS_LABEL_SHOWN>False</IS_LABEL_SHOWN><IS_DIRECTED>True</IS_DIRECTED><EDGES></EDGES><LINE_WIDTH>2</LINE_WIDTH><LINE_COLOR>230;0;0</LINE_COLOR><IS_NEEDED_ON_DIAGRAM>True</IS_NEEDED_ON_DIAGRAM><REAL_LINE_WIDTH>200</REAL_LINE_WIDTH></BON_INHERITANCE_FIGURE><BON_INHERITANCE_FIGURE TARGET="A1B353BF-1432-4684-B2D5-335DE303F2FE" SOURCE="5AAF8D75-BA4B-4513-AEA5-DA6FCC7F6526"><IS_SELECTED>False</IS_SELECTED><IS_LABEL_SHOWN>False</IS_LABEL_SHOWN><IS_DIRECTED>True</IS_DIRECTED><EDGES></EDGES><LINE_WIDTH>2</LINE_WIDTH><LINE_COLOR>230;0;0</LINE_COLOR><IS_NEEDED_ON_DIAGRAM>True</IS_NEEDED_ON_DIAGRAM><REAL_LINE_WIDTH>200</REAL_LINE_WIDTH></BON_INHERITANCE_FIGURE><BON_INHERITANCE_FIGURE TARGET="FBC39098-FEEF-4AD8-9000-892BA18608D4" SOURCE="A1B353BF-1432-4684-B2D5-335DE303F2FE"><IS_SELECTED>False</IS_SELECTED><IS_LABEL_SHOWN>False</IS_LABEL_SHOWN><IS_DIRECTED>True</IS_DIRECTED><EDGES></EDGES><LINE_WIDTH>2</LINE_WIDTH><LINE_COLOR>230;0;0</LINE_COLOR><IS_NEEDED_ON_DIAGRAM>True</IS_NEEDED_ON_DIAGRAM><REAL_LINE_WIDTH>200</REAL_LINE_WIDTH></BON_INHERITANCE_FIGURE></ROOT_ELEMENTS></VIEW></EIFFEL_CLASS_DIAGRAM>